{
  "Workflows": [
    {
      "Path": null,
      "SortBy": 0,
      "VariablesSectionElementsOrder": [],
      "ArgumentsSectionElementsOrder": null,
      "ConstantsSectionElementsOrder": null,
      "AddedNamespaces": null
    },
    {
      "Path": "Main.xaml",
      "SortBy": 0,
      "VariablesSectionElementsOrder": [
        "RutaPendientes&Sequence_5",
        "RutaCompletados&Sequence_5",
        "Archivos&Sequence_5",
        "RutaArchivo&Sequence_5",
        "LogProcesos&Sequence_5",
        "TemplateExcel&Sequence_5",
        "NombreCompania&Sequence_5",
        "Pais&Sequence_5",
        "RFC_NIT&Sequence_5",
        "DigVerificacion&Sequence_5",
        "RutaPDF&Sequence_5",
        "NombreMarcaPrincipal&Sequence_5",
        "idNavegador2&Sequence_5",
        "listMails&Sequence_5",
        "LogFile&Sequence_5",
        "RutaDescargasChi&Sequence_5",
        "RutaDescargaPhi&Sequence_5",
        "TaskConfirmation&Sequence_5",
        "UltimaFila&Sequence_5",
        "dtCompañia&StateMachine_1",
        "dtConfiguracion&StateMachine_1",
        "dtVariaciones&StateMachine_1",
        "idNavegador&StateMachine_1",
        "Paso&StateMachine_1",
        "counterException&StateMachine_1",
        "EstadoInicializacion&State_1",
        "Height&Sequence_14",
        "Width&Sequence_14",
        "Script_Path&Sequence_14",
        "ExcelWindow&Sequence_2",
        "Prueba&Sequence_1",
        "dtVariacionesTmp&Sequence_9",
        "EstadoProcesamiento&State_3",
        "counter&State_3",
        "NombrePDF&State_3",
        "ArchivosExcel&State_3",
        "NombreExcel&State_3",
        "dtSortConfig&State_3",
        "dictSortOrder&State_3",
        "dtDataOrdered&State_3",
        "URL_Proceso&TryCatch_2",
        "CarpetaDestino&TryCatch_2",
        "NombreID_URL&TryCatch_2",
        "Encontrado&TryCatch_2",
        "EncontradoDT&TryCatch_2",
        "Keywords&Sequence_16",
        "VariacionesPCAOB&Sequence_711",
        "ColorGris&Sequence_570",
        "Rango&Sequence_570",
        "OrderToFind&Sequence_570",
        "Script_Path&State_2",
        "Width&State_2",
        "Height&State_2"
      ],
      "ArgumentsSectionElementsOrder": [],
      "ConstantsSectionElementsOrder": null,
      "AddedNamespaces": null
    },
    {
      "Path": "Frameworks/Config.xaml",
      "SortBy": 0,
      "VariablesSectionElementsOrder": [
        "Mails&Sequence_1"
      ],
      "ArgumentsSectionElementsOrder": [
        "listMails"
      ],
      "ConstantsSectionElementsOrder": null,
      "AddedNamespaces": null
    },
    {
      "Path": "Frameworks/Resultados Template.xaml",
      "SortBy": 0,
      "VariablesSectionElementsOrder": [
        "VariacionCompañia&Sequence_1",
        "Otro&Sequence_1",
        "Pais&Sequence_1",
        "RFC_NIT&Sequence_1",
        "DigVerif&Sequence_1",
        "PersonaMoral&Sequence_1",
        "DatosAccionistas&Sequence_1",
        "Contador&Sequence_1",
        "PersonaFisica&Sequence_1",
        "PersonaFisicaDT&Sequence_1",
        "Variacion&Sequence_1",
        "NombreCompleto&Sequence_1",
        "ExisteFolder&Sequence_1",
        "ID_URL&Sequence_1",
        "RutaCarpeta&Sequence_1",
        "DT_ResultadosPrevios&Sequence_1",
        "ResultadoPrevio&Sequence_1",
        "DatosEjecutivos&Sequence_1",
        "variable1&Sequence_1",
        "NombreCompañia&Sequence_1"
      ],
      "ArgumentsSectionElementsOrder": [
        "RutaPendientes",
        "RutaArchivo"
      ],
      "ConstantsSectionElementsOrder": null,
      "AddedNamespaces": null
    },
    {
      "Path": "Procesos/Theta - General.xaml",
      "SortBy": 0,
      "VariablesSectionElementsOrder": [
        "contador&Sequence_1",
        "KeywordSub&Sequence_1",
        "KeywordDT&Sequence_1",
        "Keyword&Sequence_1",
        "BusquedaNegativa&Sequence_1",
        "Url&Sequence_1",
        "PaginaActual&Sequence_1",
        "ExtractDataTable&Sequence_1",
        "LargoNombreUrl&Sequence_1",
        "NombreUrl&Sequence_1",
        "existePDF&Sequence_1",
        "TipoNombreUrl&Sequence_1",
        "RndNumber&Sequence_1",
        "contadorRnd&Sequence_1",
        "NextItem&Sequence_1",
        "URLTemp&Sequence_1",
        "WindowSaveAs&Sequence_1",
        "ExtractDataTableNext&Sequence_1",
        "intento&Sequence_1",
        "flag_RestorPages&Sequence_1",
        "VariacionTemp&Sequence_1",
        "FilePath&Sequence_1",
        "RutaSubstring&Sequence_1",
        "rutaTemp&Sequence_1",
        "NextButton&Sequence_45",
        "KeywordSinCar&Sequence_44",
        "LogoGoogle&Sequence_44",
        "WindowBrowser&Sequence_91",
        "search&Sequence_53"
      ],
      "ArgumentsSectionElementsOrder": [
        "idNavegador",
        "Busqueda",
        "ruta",
        "rol",
        "NombreID_URL",
        "URL_Proceso",
        "Encontrado",
        "Keywords",
        "EncontradoDT",
        "NombrePersonaFisica",
        "rutaResultados",
        "Busqueda2",
        "LogFile",
        "TaskConfirmation",
        "ExceptionPath"
      ],
      "ConstantsSectionElementsOrder": null,
      "AddedNamespaces": null
    },
    {
      "Path": "Procesos/Alpha.xaml",
      "SortBy": 0,
      "VariablesSectionElementsOrder": [
        "ZERO_TIMEOUT&Sequence_1",
        "didNotLoad&Sequence_5",
        "TIMEOUT&Sequence_5",
        "PaginaActual&Sequence_1",
        "contador&Sequence_1",
        "Url&Sequence_1",
        "BusquedaNegativa&Sequence_1",
        "FilePath&TryCatch_2",
        "BusquedaError&Sequence_2"
      ],
      "ArgumentsSectionElementsOrder": [
        "idNavegador",
        "Busqueda",
        "ruta",
        "rol",
        "NombreID_URL",
        "URL_Proceso",
        "Encontrado",
        "LogFile",
        "LogProcesos",
        "TaskConfirmation",
        "ExceptionPath"
      ],
      "ConstantsSectionElementsOrder": null,
      "AddedNamespaces": null
    }
  ]
}